[{"inputs":[],"stateMutability":"nonpayable","type":"constructor"},{"anonymous":false,"inputs":[{"indexed":true,"internalType":"address","name":"previousOwner","type":"address"},{"indexed":true,"internalType":"address","name":"newOwner","type":"address"}],"name":"OwnershipTransferred","type":"event"},{"anonymous":false,"inputs":[{"indexed":false,"internalType":"address","name":"user_","type":"address"},{"indexed":false,"internalType":"uint256","name":"amountUSD_","type":"uint256"},{"indexed":false,"internalType":"uint256","name":"tokenAmount_","type":"uint256"}],"name":"userBuy","type":"event"},{"anonymous":false,"inputs":[{"indexed":false,"internalType":"address","name":"user_","type":"address"},{"indexed":false,"internalType":"uint256","name":"tokenAmount_","type":"uint256"}],"name":"userClaim","type":"event"},{"inputs":[{"internalType":"uint256","name":"amountUSD_","type":"uint256"},{"internalType":"address","name":"token_","type":"address"}],"name":"buyTokens","outputs":[],"stateMutability":"payable","type":"function"},{"inputs":[],"name":"canClaim","outputs":[{"internalType":"bool","name":"","type":"bool"}],"stateMutability":"view","type":"function"},{"inputs":[],"name":"claimTokens","outputs":[],"stateMutability":"nonpayable","type":"function"},{"inputs":[],"name":"curRound","outputs":[{"internalType":"uint256","name":"","type":"uint256"}],"stateMutability":"view","type":"function"},{"inputs":[{"internalType":"address","name":"","type":"address"}],"name":"currencyAllowed","outputs":[{"internalType":"bool","name":"","type":"bool"}],"stateMutability":"view","type":"function"},{"inputs":[],"name":"maxTotalBuy","outputs":[{"internalType":"uint256","name":"","type":"uint256"}],"stateMutability":"view","type":"function"},{"inputs":[],"name":"owner","outputs":[{"internalType":"address","name":"","type":"address"}],"stateMutability":"view","type":"function"},{"inputs":[],"name":"renounceOwnership","outputs":[],"stateMutability":"nonpayable","type":"function"},{"inputs":[{"internalType":"uint256","name":"","type":"uint256"}],"name":"saleRounds","outputs":[{"internalType":"uint256","name":"roundPrice","type":"uint256"},{"internalType":"uint256","name":"roundSupply","type":"uint256"},{"internalType":"uint256","name":"roundStart","type":"uint256"},{"internalType":"uint256","name":"roundEnd","type":"uint256"},{"internalType":"uint256","name":"roundSales","type":"uint256"}],"stateMutability":"view","type":"function"},{"inputs":[],"name":"saleToken","outputs":[{"internalType":"address","name":"","type":"address"}],"stateMutability":"view","type":"function"},{"inputs":[{"internalType":"bool","name":"canClaim_","type":"bool"}],"name":"setClaimStatus","outputs":[],"stateMutability":"nonpayable","type":"function"},{"inputs":[{"internalType":"uint256","name":"price_","type":"uint256"},{"internalType":"uint256","name":"supply_","type":"uint256"},{"internalType":"uint256","name":"days_","type":"uint256"}],"name":"startNewRound","outputs":[],"stateMutability":"nonpayable","type":"function"},{"inputs":[],"name":"totalClaimed","outputs":[{"internalType":"uint256","name":"","type":"uint256"}],"stateMutability":"view","type":"function"},{"inputs":[],"name":"totalTokensSold","outputs":[{"internalType":"uint256","name":"","type":"uint256"}],"stateMutability":"view","type":"function"},{"inputs":[],"name":"totalUSDCollected","outputs":[{"internalType":"uint256","name":"","type":"uint256"}],"stateMutability":"view","type":"function"},{"inputs":[{"internalType":"address","name":"newOwner","type":"address"}],"name":"transferOwnership","outputs":[],"stateMutability":"nonpayable","type":"function"},{"inputs":[{"internalType":"address","name":"","type":"address"}],"name":"userBuys","outputs":[{"internalType":"uint256","name":"totalUSD","type":"uint256"},{"internalType":"uint256","name":"totalTokens","type":"uint256"},{"internalType":"bool","name":"hasClaimed","type":"bool"}],"stateMutability":"view","type":"function"},{"inputs":[],"name":"withdrawBNB","outputs":[],"stateMutability":"nonpayable","type":"function"},{"inputs":[{"internalType":"address","name":"token_","type":"address"}],"name":"withdrawToken","outputs":[],"stateMutability":"nonpayable","type":"function"}]